poppy/__init__.py
poppy/core/__init__.py
poppy/core/command.py
poppy/core/conf/__init__.py
poppy/core/conf/default_settings.py
poppy/core/conf/logger.json
poppy/core/configuration.py
poppy/core/db/__init__.py
poppy/core/db/base.py
poppy/core/db/connector.py
poppy/core/db/database.py
poppy/core/db/dry_runner.py
poppy/core/db/handlers.py
poppy/core/db/models/__init__.py
poppy/core/db/non_null_column.py
poppy/core/generic/__init__.py
poppy/core/generic/cache.py
poppy/core/generic/dot_dict.py
poppy/core/generic/graph.py
poppy/core/generic/manager.py
poppy/core/generic/metaclasses.py
poppy/core/generic/paths.py
poppy/core/generic/requests.py
poppy/core/generic/signals.py
poppy/core/generic/timer.py
poppy/core/logger.py
poppy/core/loop.py
poppy/core/management/__init__.py
poppy/core/management/commands.py
poppy/core/management/templates/pipeline_template/config.json-tpl
poppy/core/management/templates/pipeline_template/descriptor.json-tpl
poppy/core/management/templates/pipeline_template/manage.py
poppy/core/management/templates/pipeline_template/requirements.txt
poppy/core/management/templates/pipeline_template/settings.py-tpl
poppy/core/management/templates/plugin_template/MANIFEST.in-tpl
poppy/core/management/templates/plugin_template/README.rst-tpl
poppy/core/management/templates/plugin_template/plugin_namespace/__init__.py-tpl
poppy/core/management/templates/plugin_template/plugin_namespace/plugin_name/__init__.py-tpl
poppy/core/management/templates/plugin_template/plugin_namespace/plugin_name/commands.py-tpl
poppy/core/management/templates/plugin_template/plugin_namespace/plugin_name/descriptor.json-tpl
poppy/core/management/templates/plugin_template/plugin_namespace/plugin_name/models/__init__.py-tpl
poppy/core/management/templates/plugin_template/plugin_namespace/plugin_name/models/versions/README.rst
poppy/core/management/templates/plugin_template/plugin_namespace/plugin_name/tasks.py-tpl
poppy_core-0.12.3.dist-info/LICENSE
poppy_core-0.12.3.dist-info/METADATA
poppy_core-0.12.3.dist-info/WHEEL
poppy_core-0.12.3.dist-info/entry_points.txt
poppy_core-0.12.3.dist-info/RECORD
