Metadata-Version: 2.3
Name: poppy-core
Version: 0.12.3
Summary: POPPy: Plugin-Oriented Pipeline for Python
Home-page: https://gitlab.obspm.fr/POPPy/POPPyCore
License: CeCILL 2.1
Author: ROC Team
Author-email: roc.support@sympa.obspm.fr
Requires-Python: >=3.9,<4
Classifier: License :: Other/Proprietary License
Classifier: Programming Language :: Python :: 3
Classifier: Programming Language :: Python :: 3.9
Classifier: Programming Language :: Python :: 3.10
Classifier: Programming Language :: Python :: 3.11
Classifier: Programming Language :: Python :: 3.12
Classifier: Programming Language :: Python :: 3.13
Requires-Dist: alembic (>=1,<2)
Requires-Dist: declic (>=1,<2)
Requires-Dist: jsonschema (>=4,<5)
Requires-Dist: packaging
Requires-Dist: psycopg2-binary (>=2,<3)
Requires-Dist: sqlalchemy (>=2,<3)
Project-URL: Repository, https://gitlab.obspm.fr/POPPy/POPPyCore
